todds_timer/__init__.py
todds_timer/todds_timer.py
todds_timer-2025.9.12.dist-info/METADATA
todds_timer-2025.9.12.dist-info/WHEEL
todds_timer-2025.9.12.dist-info/licenses/LICENSE
todds_timer-2025.9.12.dist-info/RECORD
