Metadata-Version: 2.4
Name: todds_timer
Version: 2025.9.12
Summary: A custom timer utility for Python
Project-URL: Homepage, https://github.com/tch521/todds_timer
Project-URL: Bug Tracker, https://github.com/tch521/todds_timer/issues
Author-email: Todd <73101886+tch521@users.noreply.github.com>
License-File: LICENSE
Classifier: License :: OSI Approved :: MIT License
Classifier: Operating System :: OS Independent
Classifier: Programming Language :: Python :: 3
Requires-Python: >=3.10
